purifyllm/main.py
purifyllm/py.typed
purifyllm-0.1.1.dist-info/licenses/LICENSE
purifyllm-0.1.1.dist-info/METADATA
purifyllm-0.1.1.dist-info/WHEEL
purifyllm-0.1.1.dist-info/entry_points.txt
purifyllm-0.1.1.dist-info/top_level.txt
purifyllm-0.1.1.dist-info/RECORD
