Metadata-Version: 2.4
Name: purifyllm
Version: 0.1.1
Summary: purifyllm
Author-email: William Droz <william.droz.ch@gmail.com>
License: MIT License
Classifier: Intended Audience :: Developers
Requires-Python: >=3.11
License-File: LICENSE
Provides-Extra: dev
Requires-Dist: pytest>=8.4.1; extra == "dev"
Dynamic: license-file
